ncompasslib/__init__.py
ncompasslib/immutable.py
ncompasslib/trait.py
tests/__init__.py
tests/test_immutable.py
tests/test_package.py
tests/test_trait.py
ncompasslib-0.0.1.post7.dist-info/METADATA
ncompasslib-0.0.1.post7.dist-info/WHEEL
ncompasslib-0.0.1.post7.dist-info/top_level.txt
ncompasslib-0.0.1.post7.dist-info/RECORD
